{"basket_id": "2ad3228a-78c6-4051-91df-a915e0944c9d", "timestamp": "2020-04-04T15:12:10.963Z", "items": [{"item_id": "cc8de497-6b41-4c48-894d-42fe24327c9b", "product_name": "", "category": "CITRUS"}, {"item_id": "74bce41e-855b-41e6-935d-838fb5f50bca", "product_name": "Nestle Shredded Wheat Bitesize Cereal 750G", "category": "PASTA"}, {"item_id": "a2e326e5-5a70-4e72-85ce-a84b91c39a57", "product_name": "Nestle Cheerios Cinnamon Oat Crisp Cereal 440g", "category": "BACON"}, {"item_id": "8ac540fb-5f7a-4a30-9844-ab9ad513ee61", "product_name": "Alpro Hazelnut Drink Uht 1l", "category": "FISH COUNTER"}, {"item_id": "e93b2613-97c8-428c-b300-d52db15fc8b3", "product_name": "Fairy All in One Original Dishwasher Tablets 84 per pack", "category": "BABY FOOD"}, {"item_id": "3a8de8da-b3c0-4c25-8bbd-19c05b7df26d", "product_name": "Fairy Lemon Washing Up Liquid 780Ml", "category": "HAIR CARE"}, {"item_id": "17fd6607-aba1-4c7b-a0c7-f78c32779e0b", "product_name": "Cadbury Animals Mini Biscuits 6 Pack 6x22g", "category": "PASTA"}]}