{"basket_id": "361e7f0b-2e11-4bef-93f5-e24ab16d17d8", "timestamp": "2020-04-02T15:12:10.735Z", "items": [{"item_id": "f181f5c4-cd29-417e-a198-6603db0d98f2", "product_name": "Tassimo 16 Twinings English Breakfast Pods 40g", "category": "ORIENTAL"}, {"item_id": "dc5e1e7e-7e65-435f-b880-70b57fe41b9d", "product_name": "Cadbury Flake Ice Cream 480Ml", "category": "BACON"}, {"item_id": "45ce044c-0d48-4976-be3d-1080c449ec8d", "product_name": "Nestle Low Sugar Oat Cheerios 325g", "category": "FISH COUNTER"}, {"item_id": "94a881c1-3424-41e8-92f8-d45cc5c2ecf5", "product_name": "Twinings Decaf Earl Grey Tea Bags 50s 125g", "category": "HAIR CARE"}, {"item_id": "53710a9d-e394-485d-bc7f-60ffd5cc9b64", "product_name": "Cadbury Flake Ice Cream Tub 480ml", "category": "CAKE"}, {"item_id": "97962e7c-9451-45bf-b2a5-da66506c8423", "product_name": "Fairy Washing Up Liquid Apple Orchard 820Ml", "category": "YOGURTS"}, {"item_id": "85f1374a-f1f7-43cd-8642-455dfaa63a96", "product_name": "Fairy Non Biological Pods 15 Washing Capsules", "category": "BACON"}, {"item_id": "ace99d8f-d71f-4427-b7af-795f59480593", "product_name": "", "category": "YOGURTS"}, {"item_id": "afba629e-967e-4f1b-8c9d-2307148b59ab", "product_name": "Heinz Farleys Rusk Reduced Sugar 9pk 150g", "category": "CAKE"}, {"item_id": "1560aec2-b9b3-4469-9668-ff70dea93acc", "product_name": "Alpro Soya Light Longlife Drink Alternative 1 Litre", "category": "ORIENTAL"}, {"item_id": "32b00e99-5e77-4548-9025-a8cbc53d586c", "product_name": "Nestle Shredded Wheat Honey Nut Cereal 500g", "category": "FISH COUNTER"}, {"item_id": "4f1d0ac7-aaf8-4db4-9321-afa097e15f05", "product_name": "Twinings Raspberry And Strawberry Tea Bags 20each", "category": "YOGURTS"}, {"item_id": "7f5d1610-b94a-4746-a04a-39d44d42cb8c", "product_name": "Alpen Original Muesli 1.3kg", "category": "ORIENTAL"}, {"item_id": "83dc2900-9481-41a6-8fa1-2c8f7213d573", "product_name": "", "category": "YOGURTS"}, {"item_id": "2326f192-1f45-4769-97bb-8aa93607a393", "product_name": "", "category": "FISH COUNTER"}, {"item_id": "c2b2a162-f83d-477e-8abb-e9c47b38a364", "product_name": "Tropicana Essentials Vitality Juice Drink 750ml", "category": "HAIR CARE"}, {"item_id": "d2850ea5-f13e-4ad0-833a-23552e9aa8f1", "product_name": "", "category": "HAIR CARE"}, {"item_id": "026d1dce-1887-4625-804f-35d36fe692f1", "product_name": "Fairy non bio pods x15", "category": "BABY FOOD"}, {"item_id": "69d7adb9-64c2-4124-b722-20fa2cde210a", "product_name": "", "category": "BACON"}, {"item_id": "58986463-6ac6-45ac-849c-2979c0af44e1", "product_name": "", "category": "FISH COUNTER"}]}