{"basket_id": "3677b28d-db42-4460-9711-8710b239ef57", "timestamp": "2020-05-22T15:12:10.701Z", "items": [{"item_id": "8b09b2ad-4ef8-49a8-84cc-3a56cd914db2", "product_name": "Fairy 84 All in One Capsules Original 1134g", "category": "CITRUS"}, {"item_id": "f77eaa76-7c14-4b9f-9e71-efa42566bc9d", "product_name": "Alpen Light Summer Fruits Bars 5 Pack 95G", "category": "PASTA"}, {"item_id": "8e142e78-bf80-4362-a9f8-de0f621a4a5a", "product_name": "Cadbury Animals Mini Biscuits 6 Pack 6x22g", "category": "ORIENTAL"}, {"item_id": "17ec8bef-3064-4de1-9908-18dc30f837df", "product_name": "Weight Watchers from Heinz Salmon & Broccoli Melt Ready Meal 320g", "category": "CAKE"}, {"item_id": "dd7d4ec1-b686-4ee8-b6b9-aee70b1b5b12", "product_name": "Nestle Oats And More Raisin Cereal 425G", "category": "BACON"}, {"item_id": "f79d62bb-eda2-4376-88c6-6c5522ad1c29", "product_name": "", "category": "FISH COUNTER"}, {"item_id": "5d2716a9-da48-4742-ae74-de771e6cb60a", "product_name": "Nestle Frosted Shreddies 500g", "category": "ORIENTAL"}, {"item_id": "183cdd51-f107-4f56-a35b-ba701459b9fe", "product_name": "Cadbury Crunchie Ice Cream 480ml", "category": "CAKE"}, {"item_id": "c1b16488-cff6-49b2-b11f-59166f2e76fa", "product_name": "Alpro longlife original almond drink 1litre", "category": "FISH COUNTER"}, {"item_id": "a1a1c884-9e4b-4269-8d16-163e09d6adc7", "product_name": "Alpen No Added Sugar Muesli 560g", "category": "YOGURTS"}, {"item_id": "4408815f-9e01-4cb9-be97-63abe61a5b7f", "product_name": "Nestle 4 Nobbly Bobbly Ice Creams 4x70ml", "category": "CAKE"}, {"item_id": "7f938b8c-8778-490d-ac3e-6ac549a0a703", "product_name": "Nestle Shredded Wheat Barley Spelt 475g", "category": "ORIENTAL"}, {"item_id": "24110657-1c92-4f5b-8b84-8f0a4697d053", "product_name": "", "category": "BACON"}, {"item_id": "d91847fb-00de-4370-b0ff-31e07952c26c", "product_name": "Nestle Golden Nuggets Cereal 375G", "category": "CITRUS"}, {"item_id": "7dd47579-bacf-473e-8a14-27698acc544d", "product_name": "Alpen Muesli Original 750g", "category": "PASTA"}, {"item_id": "85f88a2f-1719-4c85-bd88-928eb64407e4", "product_name": "", "category": "YOGURTS"}, {"item_id": "7c1e3813-debf-4b4a-bce3-d474093ae690", "product_name": "Cadbury Flake Ice Cream 480Ml", "category": "FISH COUNTER"}, {"item_id": "1c301479-bea0-4100-ad6e-cc47af3e732b", "product_name": "", "category": "BABY FOOD"}]}