{"basket_id": "692e041c-9335-4b67-889b-063c40937d82", "timestamp": "2020-05-13T15:12:11.271Z", "items": [{"item_id": "3aad3a0e-53c0-4634-a2ad-5ce79f784441", "product_name": "Nestle Rolo Desserts 4 x 70g", "category": "HAIR CARE"}, {"item_id": "c23fd638-fdad-4718-9611-ea2efabdb528", "product_name": "Heinz Ketchup 50% Less Sugar 435G", "category": "BACON"}, {"item_id": "6a1f9023-7a79-4712-b69f-e088f4300067", "product_name": "Cadbury Flake Ice Cream 480Ml", "category": "PASTA"}, {"item_id": "d90e898e-bfd0-4acd-b163-2bb85c0f3f59", "product_name": "", "category": "CITRUS"}, {"item_id": "44a295df-16af-49dc-8ffc-6c54403df81c", "product_name": "Weight Watchers from Heinz Salmon & Broccoli Melt Ready Meal 320g", "category": "CITRUS"}, {"item_id": "6eb31d2b-dbed-49bc-85dc-42f5f627ba1c", "product_name": "", "category": "PASTA"}, {"item_id": "b574c2d0-4bf9-4dd0-9701-80fd7fb0e726", "product_name": "Fairy Non Bio Pods Washing Liquid Capsules 15 Washes 15pk", "category": "ORIENTAL"}, {"item_id": "feb6706f-8e8c-46b0-8b34-16ae5bc56aad", "product_name": "Nestle Lion Cereal 400g", "category": "HAIR CARE"}, {"item_id": "66ea106a-3810-40c0-9fb2-48758b75f7ab", "product_name": "", "category": "BACON"}, {"item_id": "023ec907-d204-4fa0-a781-822e6f58ee03", "product_name": "", "category": "BABY FOOD"}, {"item_id": "7c3a245c-5e85-44fc-aee2-d176f4931873", "product_name": "", "category": "HAIR CARE"}, {"item_id": "6e57b5ac-a5cb-445d-a8cb-62e9c997e9e4", "product_name": "Alpro Roasted Almond Original UHT Drink 1L", "category": "BACON"}, {"item_id": "069da0ed-a829-4cb6-8b3b-8b62cf800a1b", "product_name": "Nestle Aero Milk Chocolate  Bubbles 102g", "category": "CAKE"}, {"item_id": "bb4d010b-eace-4f55-8ef9-9e2da88ed09a", "product_name": "Fairy liquid anti-bac eucalyptus 625ml", "category": "CITRUS"}, {"item_id": "31eaf0e6-9fc7-47dd-8f41-8d7a62f068f9", "product_name": "Lenor Super Concentrate Gold Orchid 37 Wash 925ml", "category": "PASTA"}, {"item_id": "15a0aa88-c75a-4fcd-9a07-e4f99744ca2d", "product_name": "Tropicana Tropical Juice 850 Ml", "category": "BABY FOOD"}, {"item_id": "dfc0f81c-2565-49a3-b157-8cc14de1c1ef", "product_name": "", "category": "BACON"}]}