{"basket_id": "7a870677-347d-43e3-851d-74b0cea22abe", "timestamp": "2020-03-20T15:12:11.367Z", "items": [{"item_id": "236a413b-3ce0-4725-b491-f51faf98168e", "product_name": "Fairy Non Biological Pods 15 Washing Capsules", "category": "HAIR CARE"}, {"item_id": "8021b37c-b4fd-42dc-9202-fc67a0efcee7", "product_name": "Fairy All in One Original Dishwasher Tablets 84 per pack", "category": "CAKE"}, {"item_id": "4de47a97-2341-4c7e-8b3d-fa31da0bd087", "product_name": "Alpro Hazelnut Drink Uht 1l", "category": "FISH COUNTER"}, {"item_id": "79002053-17be-49f4-b68a-aa3b42fb34a6", "product_name": "Lenor Ruby Jasmine 925ml", "category": "BABY FOOD"}, {"item_id": "e52b8f8b-8753-4a22-b654-12a906741f43", "product_name": "Tropicana Juice Essentials Apple And Pineapple 330Ml", "category": "PASTA"}, {"item_id": "6c12c5e0-1261-49fc-a154-89e0e04e7618", "product_name": "", "category": "CITRUS"}, {"item_id": "59bec829-087d-4bdb-ab65-4c771c1f1c8c", "product_name": "", "category": "BACON"}, {"item_id": "aaf09215-bd73-406a-8164-6724f44eb3df", "product_name": "Fairy Non Bio Pods Washing Liquid Capsules 15 per pack", "category": "BABY FOOD"}, {"item_id": "93274f7c-a7a2-4cdd-8f78-82c8a21a50b8", "product_name": "", "category": "PASTA"}, {"item_id": "dc0e70c3-8329-4633-ae8b-5eec8dd48f52", "product_name": "Fairy Anti Bacterial Eucalyptus Washing Up Liquid 615ml", "category": "BACON"}]}