{"basket_id": "7ed945c2-67d3-43ce-98c2-cde9b26dfb4f", "timestamp": "2020-03-10T15:12:10.819Z", "items": [{"item_id": "f6246a6f-0138-46d9-8c8b-04e05eaa557e", "product_name": "Tropicana Essentials Vitality Juice Drink 750ml", "category": "HAIR CARE"}, {"item_id": "58679e5c-5065-47ba-b6a8-1552a6800c64", "product_name": "Twinings English Strong Breakfast 1706 x80 Tea bags 250g", "category": "FISH COUNTER"}, {"item_id": "1102a3de-802f-4f99-ac07-dcc5fa1bf898", "product_name": "", "category": "ORIENTAL"}]}