{"basket_id": "a3ddfe5c-46d6-4c8d-845f-9de30b471a94", "timestamp": "2020-04-12T15:12:11.364Z", "items": [{"item_id": "89b62d71-a16e-406f-8d6d-fdbf4d7d0fcc", "product_name": "Fairy Antibacterial Eucalyptus 625ml", "category": "CAKE"}, {"item_id": "7ae7f197-4c5e-4dc0-97ac-102fc995df25", "product_name": "Nestle Tip Top Squirty Cream 250G", "category": "HAIR CARE"}, {"item_id": "9f2b9cd8-201a-4391-b0e4-814c82b64c61", "product_name": "", "category": "BACON"}, {"item_id": "6df556b7-3366-489f-b0a4-acf50852653a", "product_name": "Cadbury Flake Ice Cream 480Ml", "category": "BACON"}, {"item_id": "af3468d5-a83b-4ce1-a399-ddbee6d7816e", "product_name": "Nestle Lion Cereal 400g", "category": "BABY FOOD"}, {"item_id": "c8ff4312-cd4d-44f0-b545-3da09ccbcfc0", "product_name": "Heinz Farleys Rusk Reduced Sugar 9pk 150g", "category": "CITRUS"}, {"item_id": "394f8cf0-999a-4b62-9a3d-43a016841bb0", "product_name": "Lenor Fabric Conditioner Lavender & Camomile Scent 34 Washes 1.19l", "category": "BABY FOOD"}, {"item_id": "c9e33b0f-6ac8-4fd2-875d-8ed7fd6e7d60", "product_name": "Weight Watchers from Heinz Salmon & Broccoli Melt Ready Meal 320g", "category": "PASTA"}, {"item_id": "1fdcaac3-9a5e-4671-8342-85eafc325e5b", "product_name": "Twinings Decaf Earl Grey Tea Bags 50s 125g", "category": "CITRUS"}, {"item_id": "6ce4762f-55aa-4ae5-9ca9-93f8d6b527e7", "product_name": "Lenor Summer Breeze Fabric Conditioner 54 Wash 1.9L", "category": "BABY FOOD"}, {"item_id": "033f3201-8f2d-46c6-903d-f8510d9a8a78", "product_name": "Alpen Light Summer Fruits Bars 5 Pack 95G", "category": "CAKE"}, {"item_id": "8d8e8eb0-c734-4653-9b2e-d0b44fb27813", "product_name": "", "category": "YOGURTS"}, {"item_id": "260475ca-5da2-437e-9c92-5de8579a1862", "product_name": "Heinz Ketchup 50% Less Sugar 435G", "category": "CITRUS"}, {"item_id": "4aede1b5-5eb5-47b8-9a85-0fff4b11262b", "product_name": "", "category": "HAIR CARE"}, {"item_id": "74aa937e-8796-4e2a-b578-fa5f25a9bb5b", "product_name": "Cadbury Animals Mini Biscuits 6 Pack 6x22g", "category": "BACON"}, {"item_id": "960900fe-8701-4c9b-972e-3a2f6d424a86", "product_name": "Alpro Soya Light Longlife Drink Alternative 1 Litre", "category": "CAKE"}, {"item_id": "663bc42f-1bae-4e33-a6ef-01f1da44f6a3", "product_name": "Lenor Fabric Conditioner Summer Breeze Scent 54 Washes 1.9l", "category": "CITRUS"}]}