{"basket_id": "c9e1bd5c-747d-412d-a2c3-7511082cd77b", "timestamp": "2020-03-27T15:12:11.268Z", "items": [{"item_id": "821f7b2a-2d01-425a-a6a9-f151972b5002", "product_name": "Alpen Cereal No Added Sugar Muesli 1.1kg", "category": "CITRUS"}, {"item_id": "8d0b5577-b8b3-4ea2-a6eb-bd9c429166cc", "product_name": "", "category": "BABY FOOD"}, {"item_id": "f62ab6ef-773d-4626-9482-edc18b84ff44", "product_name": "", "category": "CITRUS"}, {"item_id": "b6347fa3-9118-4a38-adf1-641c4e49c26d", "product_name": "Tassimo Twinings English Breakfast Tea Pods 16 Servings", "category": "HAIR CARE"}, {"item_id": "0ef234f1-de9c-449f-86d4-94cde47d82cb", "product_name": "Tropicana Essentials Vitality Juice Drink 750ml", "category": "HAIR CARE"}, {"item_id": "16261ac7-ab9a-4447-b80f-a50b9b0ef2b5", "product_name": "", "category": "PASTA"}, {"item_id": "711bd4eb-0046-466e-8b3d-ca17cc3b8de4", "product_name": "", "category": "HAIR CARE"}, {"item_id": "ca00357d-9d47-46c0-a9df-6bd910fdd470", "product_name": "", "category": "CAKE"}, {"item_id": "3d2a7c91-3bf7-4a24-8c12-9d575f284a93", "product_name": "Alpro longlife dairy free soya strawberry drink pack of 3 3x250ml", "category": "YOGURTS"}, {"item_id": "f4779306-c095-4fd9-a3e6-6cca924d9ec1", "product_name": "Tassimo Twinings English Breakfast Tea Pods 16 Servings", "category": "BABY FOOD"}, {"item_id": "67361cf5-61d3-4a45-9b11-ca48f6bfec84", "product_name": "Nestle Tip Top Squirty Cream 250G", "category": "CAKE"}, {"item_id": "8dca7c5b-3bcb-4aa0-9b48-747808b538c2", "product_name": "Nestle Box Bowls Cereal 210g", "category": "PASTA"}]}