{"basket_id": "ffa3e432-9e74-48ee-9fe6-ac2e9b7dcd40", "timestamp": "2020-03-31T15:12:10.708Z", "items": [{"item_id": "1f54370b-9aea-473f-b1f0-d20fa3a79638", "product_name": "Fairy Lemon Washing Up Liquid 780Ml", "category": "YOGURTS"}, {"item_id": "b8d9fb6a-170f-44f9-813f-85349349f963", "product_name": "Lenor unstoppables fresh 570g", "category": "YOGURTS"}, {"item_id": "938b604d-c36b-4b24-8997-99e103ec09d3", "product_name": "Twinings Earl Grey 200 tea bags 500g", "category": "CAKE"}, {"item_id": "7f0c4dee-b3bf-4dc6-bcc4-e258d6a76cd0", "product_name": "", "category": "BABY FOOD"}, {"item_id": "6d7ab471-7dfe-4a15-bc3b-7f4ddcf0d7a6", "product_name": "Heinz Farleys Rusk Reduced Sugar 9pk 150g", "category": "FISH COUNTER"}, {"item_id": "0e662490-b7f5-4dfa-b170-68b948f10ad0", "product_name": "Tropicana Juice Essentials Apple And Pineapple 750Ml", "category": "BACON"}, {"item_id": "4694f00f-e525-431e-be25-e0d5e546f4c3", "product_name": "Lenor Super Concentrate Gold Orchid 37 Wash 925ml", "category": "BABY FOOD"}, {"item_id": "6b610cd3-fb50-4135-a18d-a3fc89904aa4", "product_name": "Alpen Original Muesli 1.3kg", "category": "HAIR CARE"}, {"item_id": "4728b2d0-d083-44ee-bdd9-5041f0a44474", "product_name": "Nestle Lion Cereal 400g", "category": "ORIENTAL"}, {"item_id": "3410c218-790a-4a96-a995-ca25f0ac34b9", "product_name": "Cadbury Wispa chocolate bar 4 pack 120g", "category": "BACON"}, {"item_id": "2c78994d-3825-4db0-9e4f-1d400469b22a", "product_name": "Lenor Super Concentrate Gold Orchid 37 Wash 925ml", "category": "PASTA"}, {"item_id": "d0ebb106-3ca3-43e7-9a23-d9f45040feda", "product_name": "Lenor Unstoppables Fresh In-Wash Scent Booster 570g", "category": "PASTA"}, {"item_id": "e93ce219-a410-4a5b-8013-c999a6bf429c", "product_name": "Nestle Oat Cheerios 375g", "category": "CAKE"}, {"item_id": "76c7b36e-e81e-47ca-9e64-e6e1b6bf2289", "product_name": "", "category": "BABY FOOD"}, {"item_id": "a7566a70-082c-4898-b497-f00c69be1f44", "product_name": "Tropicana Orange & Mango Juice 850ml", "category": "YOGURTS"}]}